currencycom/__init__.py
currencycom/client.py
python_currencycom-0.2.3.dist-info/LICENSE
python_currencycom-0.2.3.dist-info/METADATA
python_currencycom-0.2.3.dist-info/WHEEL
python_currencycom-0.2.3.dist-info/top_level.txt
python_currencycom-0.2.3.dist-info/RECORD
